Metadata-Version: 2.1
Name: galearn
Version: 0.0.2.1
Summary: Genetic Algorithms for model selection
Home-page: UNKNOWN
Author: Oliver Holl
Author-email: <oholl@ethz.ch>
License: UNKNOWN
Keywords: machine learning,hyperparameter tuning,hyperparameter,scikit-learn
Platform: UNKNOWN
Classifier: Development Status :: 1 - Planning
Classifier: Intended Audience :: Developers
Classifier: Programming Language :: Python :: 3
Classifier: Operating System :: Unix
Classifier: Operating System :: MacOS :: MacOS X
Classifier: Operating System :: Microsoft :: Windows
License-File: LICENCE.txt
